{"cameraMode":{"drawMode":0,"name":"Shaded","section":"Shading Mode"},"sceneLighting":false,"audioPlay":false,"sceneViewState":{"m_AlwaysRefresh":false,"showFog":false,"showSkybox":false,"showFlares":true,"showImageEffects":true,"showParticleSystems":true,"showVisualEffectGraphs":true,"m_FxEnabled":true},"in2DMode":false,"pivot":{"x":388.4061584472656,"y":125.2385025024414,"z":-530.285400390625},"rotation":{"x":-0.43347761034965517,"y":0.5555607080459595,"z":-0.42240265011787417,"w":-0.5700717568397522},"size":1.2247449159622193,"orthographic":false}